memizer/__init__.py
memizer-1.0.0.dist-info/LICENSE
memizer-1.0.0.dist-info/METADATA
memizer-1.0.0.dist-info/WHEEL
memizer-1.0.0.dist-info/entry_points.txt
memizer-1.0.0.dist-info/top_level.txt
memizer-1.0.0.dist-info/RECORD
