Metadata-Version: 2.1
Name: memizer
Version: 1.0.0
Summary: Displays a meme
Author-email: Miloš Roknić <roknic.milos.994@gmail.com>
License: MIT License
Project-URL: Homepage, https://github.com/roknicmilos/memizer
Keywords: meme,memizer
Classifier: License :: OSI Approved :: MIT License
Classifier: Programming Language :: Python
Classifier: Programming Language :: Python :: 3
Requires-Python: >=3.9
License-File: LICENSE
